endorser/__init__.py
endorser/converter.py
endorser/error.py
endorser/schema.py
endorser/validator.py
test/__init__.py
test/converter_test.py
test/data.py
test/schema_test.py
test/validator_test.py
endorser-0.24.dist-info/LICENSE
endorser-0.24.dist-info/METADATA
endorser-0.24.dist-info/WHEEL
endorser-0.24.dist-info/top_level.txt
endorser-0.24.dist-info/RECORD
