Metadata-Version: 2.1
Name: endorser
Version: 0.24
Summary: Annotation based python object validator
Home-page: https://github.com/watsta/endorser
Author: Krisztian Toth
Author-email: tkrisztiana@gmail.com
License: UNKNOWN
Keywords: object validator validate converter convert
Platform: UNKNOWN
Classifier: Programming Language :: Python :: 3
Classifier: License :: OSI Approved :: MIT License
Classifier: Operating System :: OS Independent
